bookmark/__init__.py
bookmark/sql_bookmarker.py
tests/__init__.py
tests/test_sqlalchemy_bookmarker.py
bookmarker-0.0.2.dist-info/METADATA
bookmarker-0.0.2.dist-info/WHEEL
bookmarker-0.0.2.dist-info/top_level.txt
bookmarker-0.0.2.dist-info/RECORD
