Metadata-Version: 2.1
Name: bookmarker
Version: 0.0.2
Summary: Library for adding a bookmark
Home-page: https://github.com/shuttl-tech/shuttl_workflows
Author: Shuttl
Author-email: swarnima.gupta@shuttl.com
License: MIT
Platform: UNKNOWN
Classifier: Programming Language :: Python :: 3.7
Classifier: License :: OSI Approved :: MIT License
Classifier: Operating System :: OS Independent
Requires-Dist: Flask-SQLAlchemy
Requires-Dist: SQLAlchemy
Requires-Dist: pytz
Provides-Extra: test
Requires-Dist: pytest ; extra == 'test'
Requires-Dist: pytest-runner ; extra == 'test'
Requires-Dist: pytest-cov ; extra == 'test'
Requires-Dist: pytest-pep8 ; extra == 'test'
